genpattern/__init__.py
genpattern/genpattern.dll
genpattern/genpattern.lib
genpattern/loader.py
genpattern-0.0.3.dist-info/METADATA
genpattern-0.0.3.dist-info/WHEEL
genpattern-0.0.3.dist-info/licenses/LICENSE
genpattern-0.0.3.dist-info/licenses/NOTICE
genpattern-0.0.3.dist-info/licenses/licenses/LLVM.txt
genpattern-0.0.3.dist-info/licenses/licenses/musl.txt
genpattern-0.0.3.dist-info/RECORD
