Metadata-Version: 2.4
Name: genpattern
Version: 0.0.3
Summary: A generator for random, seamless patterned textures from layers with alpha transparency
License-File: LICENSE
License-File: licenses/LLVM.txt
License-File: licenses/musl.txt
License-File: NOTICE
Project-URL: Homepage, https://github.com/nouveau-nvc0/genpattern
Project-URL: Repository, https://github.com/nouveau-nvc0/genpattern.git
Project-URL: Documentation, https://github.com/nouveau-nvc0/genpattern#readme
Requires-Python: >=3.10
Provides-Extra: test
Requires-Dist: pytest>=7.0; extra == "test"
Requires-Dist: Pillow>=9.0; extra == "test"
